kgschemas/__init__.py
kgschemas/com/__init__.py
kgschemas/com/storm/__init__.py
kgschemas/com/storm/kg/__init__.py
kgschemas/com/storm/kg/common/CommunicationMode.py
kgschemas/com/storm/kg/common/Company.py
kgschemas/com/storm/kg/common/Country.py
kgschemas/com/storm/kg/common/Document.py
kgschemas/com/storm/kg/common/DocumentType.py
kgschemas/com/storm/kg/common/GeoDocumentReference.py
kgschemas/com/storm/kg/common/Project.py
kgschemas/com/storm/kg/common/__init__.py
kgschemas/com/storm/kg/common/metadata/AuditRecord.py
kgschemas/com/storm/kg/common/metadata/ComplianceRecord.py
kgschemas/com/storm/kg/common/metadata/MetadataRecord.py
kgschemas/com/storm/kg/common/metadata/ProvenanceRecord.py
kgschemas/com/storm/kg/common/metadata/TransformationRecord.py
kgschemas/com/storm/kg/common/metadata/__init__.py
kgschemas/com/storm/kg/common/units/AmpereRecord.py
kgschemas/com/storm/kg/common/units/AngleRecord.py
kgschemas/com/storm/kg/common/units/AngularVelocityRecord.py
kgschemas/com/storm/kg/common/units/FrequencyRecord.py
kgschemas/com/storm/kg/common/units/LengthRecord.py
kgschemas/com/storm/kg/common/units/MassRecord.py
kgschemas/com/storm/kg/common/units/PressureRecord.py
kgschemas/com/storm/kg/common/units/TemperatureRecord.py
kgschemas/com/storm/kg/common/units/TimeRecord.py
kgschemas/com/storm/kg/common/units/UnitlessRecord.py
kgschemas/com/storm/kg/common/units/VelocityRecord.py
kgschemas/com/storm/kg/common/units/VoltRecord.py
kgschemas/com/storm/kg/common/units/WattRecord.py
kgschemas/com/storm/kg/common/units/__init__.py
kgschemas/com/storm/kg/facility/FunctionalLocation.py
kgschemas/com/storm/kg/facility/ModelFunctionalLocation.py
kgschemas/com/storm/kg/facility/OnshoreCable.py
kgschemas/com/storm/kg/facility/OnshoreOffice.py
kgschemas/com/storm/kg/facility/OnshoreSubstation.py
kgschemas/com/storm/kg/facility/OnshoreSubstationGrid.py
kgschemas/com/storm/kg/facility/OnshoreSubstationWindFarm.py
kgschemas/com/storm/kg/facility/OnshoreWarehouse.py
kgschemas-31.0.1.dist-info/METADATA
kgschemas-31.0.1.dist-info/WHEEL
kgschemas-31.0.1.dist-info/top_level.txt
kgschemas-31.0.1.dist-info/RECORD
