Metadata-Version: 2.1
Name: kgschemas
Version: 31.0.1
Summary: Knowledge Graph Schemas
Author: Dominic Stevenson
Author-email: dstev@equinor.com
Requires-Dist: pydantic
